Metadata-Version: 1.0
Name: antlr4-python2-runtime-thieman
Version: 4.10.1
Summary: ANTLR 4.10.1 runtime for Python 2.7.12
Home-page: http://www.antlr.org
Author: Eric Vergnaud, Terence Parr, Sam Harwell
Author-email: eric.vergnaud@wanadoo.fr
License: BSD
Platform: UNKNOWN
